setup.py
polymath_distribution/Binomialdistribution.py
polymath_distribution/Gaussiandistribution.py
polymath_distribution/Generaldistribution.py
polymath_distribution/__init__.py
polymath_distribution.egg-info/PKG-INFO
polymath_distribution.egg-info/SOURCES.txt
polymath_distribution.egg-info/dependency_links.txt
polymath_distribution.egg-info/not-zip-safe
polymath_distribution.egg-info/top_level.txt