Metadata-Version: 1.0
Name: polymath-distribution
Version: 0.1
Summary: Gaussian and Binomial distributions
Home-page: UNKNOWN
Author: Olarinde Alli
Author-email: polymathalli@gmail.com
License: UNKNOWN
Platform: UNKNOWN
